aircraft_list/__init__.py
aircraft_list/aircraft_list.py
aircraft_list/aircraft_model_list.csv
aircraft_list-2.5.dist-info/LICENSE
aircraft_list-2.5.dist-info/METADATA
aircraft_list-2.5.dist-info/WHEEL
aircraft_list-2.5.dist-info/top_level.txt
aircraft_list-2.5.dist-info/RECORD
